AUTHORS
LICENSE
README.md
setup.cfg
setup.py
botasaurus/__init__.py
botasaurus/beep_utils.py
botasaurus/botasaurus_storage.py
botasaurus/browser.py
botasaurus/browser_decorator.py
botasaurus/bt.py
botasaurus/cache.py
botasaurus/calc_max_parallel_browsers.py
botasaurus/cl.py
botasaurus/config.py
botasaurus/create_request.py
botasaurus/decorator_helpers.py
botasaurus/decorators_common.py
botasaurus/decorators_utils.py
botasaurus/device.py
botasaurus/dontcache.py
botasaurus/env.py
botasaurus/formats.py
botasaurus/ip_utils.py
botasaurus/lang.py
botasaurus/links.py
botasaurus/list_utils.py
botasaurus/local_storage.py
botasaurus/output.py
botasaurus/profiles.py
botasaurus/request.py
botasaurus/request_decorator.py
botasaurus/sitemap.py
botasaurus/soupify.py
botasaurus/string_utils.py
botasaurus/task.py
botasaurus/task_decorator.py
botasaurus/thread_with_result.py
botasaurus/user_agent.py
botasaurus/utils.py
botasaurus/window_size.py
botasaurus.egg-info/PKG-INFO
botasaurus.egg-info/SOURCES.txt
botasaurus.egg-info/dependency_links.txt
botasaurus.egg-info/requires.txt
botasaurus.egg-info/top_level.txt