Metadata-Version: 2.1
Name: botasaurus
Version: 4.0.54
Summary: The All in One Web Scraping Framework
Author: Chetan Jain
Author-email: chetan@omkar.cloud
Maintainer: Chetan Jain
Maintainer-email: chetan@omkar.cloud
License: MIT
Project-URL: Documentation, https://omkar.cloud/botasaurus/
Project-URL: Source, https://github.com/omkarcloud/botasaurus
Project-URL: Tracker, https://github.com/omkarcloud/botasaurus/issues
Keywords: crawler,framework,scraping,crawling,web-scraping,web-scraping-python,cloudflare-bypass,anti-detection,bot-detection,automation,webdriver,browser
Classifier: Framework :: Scrapy
Classifier: Development Status :: 5 - Production/Stable
Classifier: Environment :: Console
Classifier: Intended Audience :: Developers
Classifier: License :: OSI Approved :: MIT License
Classifier: Operating System :: OS Independent
Classifier: Programming Language :: Python
Classifier: Programming Language :: Python :: 3
Classifier: Programming Language :: Python :: 3.7
Classifier: Programming Language :: Python :: 3.8
Classifier: Programming Language :: Python :: 3.9
Classifier: Programming Language :: Python :: 3.10
Classifier: Programming Language :: Python :: 3.11
Classifier: Programming Language :: Python :: Implementation :: CPython
Classifier: Programming Language :: Python :: Implementation :: PyPy
Classifier: Topic :: Internet :: WWW/HTTP
Classifier: Topic :: Software Development :: Libraries :: Application Frameworks
Classifier: Topic :: Software Development :: Libraries :: Python Modules
Requires-Python: >=3.7
License-File: LICENSE
License-File: AUTHORS
Requires-Dist: psutil
Requires-Dist: javascript_fixes
Requires-Dist: requests
Requires-Dist: joblib>=1.3.2
Requires-Dist: beautifulsoup4>=4.11.2
Requires-Dist: lxml>=5.2.2
Requires-Dist: openpyxl
Requires-Dist: close_chrome
Requires-Dist: botasaurus-api
Requires-Dist: botasaurus-driver
Requires-Dist: bota
Requires-Dist: botasaurus-proxy-authentication
Requires-Dist: botasaurus-requests
